{
  "previous_count": 104,
  "current_count": 104,
  "new_count": 0,
  "removed_count": 0,
  "changed_count": 104,
  "new_matches": [],
  "removed_matches": [],
  "changed_matches": [
    {
      "stable_id": "fifa-wc2026-match-001",
      "changes": [
        {
          "field": "is_brazil_match",
          "before": null,
          "after": false
        }
      ]
    },
    {
      "stable_id": "fifa-wc2026-match-002",
      "changes": [
        {
          "field": "is_brazil_match",
          "before": null,
          "after": false
        }
      ]
    },
    {
      "stable_id": "fifa-wc2026-match-003",
      "changes": [
        {
          "field": "is_brazil_match",
          "before": null,
          "after": false
        }
      ]
    },
    {
      "stable_id": "fifa-wc2026-match-004",
      "changes": [
        {
          "field": "is_brazil_match",
          "before": null,
          "after": false
        }
      ]
    },
    {
      "stable_id": "fifa-wc2026-match-005",
      "changes": [
        {
          "field": "is_brazil_match",
          "before": null,
          "after": false
        }
      ]
    },
    {
      "stable_id": "fifa-wc2026-match-006",
      "changes": [
        {
          "field": "is_brazil_match",
          "before": null,
          "after": false
        }
      ]
    },
    {
      "stable_id": "fifa-wc2026-match-007",
      "changes": [
        {
          "field": "is_brazil_match",
          "before": null,
          "after": true
        }
      ]
    },
    {
      "stable_id": "fifa-wc2026-match-008",
      "changes": [
        {
          "field": "is_brazil_match",
          "before": null,
          "after": false
        }
      ]
    },
    {
      "stable_id": "fifa-wc2026-match-009",
      "changes": [
        {
          "field": "is_brazil_match",
          "before": null,
          "after": false
        }
      ]
    },
    {
      "stable_id": "fifa-wc2026-match-010",
      "changes": [
        {
          "field": "is_brazil_match",
          "before": null,
          "after": false
        }
      ]
    },
    {
      "stable_id": "fifa-wc2026-match-011",
      "changes": [
        {
          "field": "is_brazil_match",
          "before": null,
          "after": false
        }
      ]
    },
    {
      "stable_id": "fifa-wc2026-match-012",
      "changes": [
        {
          "field": "is_brazil_match",
          "before": null,
          "after": false
        }
      ]
    },
    {
      "stable_id": "fifa-wc2026-match-013",
      "changes": [
        {
          "field": "is_brazil_match",
          "before": null,
          "after": false
        }
      ]
    },
    {
      "stable_id": "fifa-wc2026-match-014",
      "changes": [
        {
          "field": "is_brazil_match",
          "before": null,
          "after": false
        }
      ]
    },
    {
      "stable_id": "fifa-wc2026-match-015",
      "changes": [
        {
          "field": "is_brazil_match",
          "before": null,
          "after": false
        }
      ]
    },
    {
      "stable_id": "fifa-wc2026-match-016",
      "changes": [
        {
          "field": "is_brazil_match",
          "before": null,
          "after": false
        }
      ]
    },
    {
      "stable_id": "fifa-wc2026-match-017",
      "changes": [
        {
          "field": "is_brazil_match",
          "before": null,
          "after": false
        }
      ]
    },
    {
      "stable_id": "fifa-wc2026-match-018",
      "changes": [
        {
          "field": "is_brazil_match",
          "before": null,
          "after": false
        }
      ]
    },
    {
      "stable_id": "fifa-wc2026-match-019",
      "changes": [
        {
          "field": "is_brazil_match",
          "before": null,
          "after": false
        }
      ]
    },
    {
      "stable_id": "fifa-wc2026-match-020",
      "changes": [
        {
          "field": "is_brazil_match",
          "before": null,
          "after": false
        }
      ]
    },
    {
      "stable_id": "fifa-wc2026-match-021",
      "changes": [
        {
          "field": "is_brazil_match",
          "before": null,
          "after": false
        }
      ]
    },
    {
      "stable_id": "fifa-wc2026-match-022",
      "changes": [
        {
          "field": "is_brazil_match",
          "before": null,
          "after": false
        }
      ]
    },
    {
      "stable_id": "fifa-wc2026-match-023",
      "changes": [
        {
          "field": "is_brazil_match",
          "before": null,
          "after": false
        }
      ]
    },
    {
      "stable_id": "fifa-wc2026-match-024",
      "changes": [
        {
          "field": "is_brazil_match",
          "before": null,
          "after": false
        }
      ]
    },
    {
      "stable_id": "fifa-wc2026-match-025",
      "changes": [
        {
          "field": "is_brazil_match",
          "before": null,
          "after": false
        }
      ]
    },
    {
      "stable_id": "fifa-wc2026-match-026",
      "changes": [
        {
          "field": "is_brazil_match",
          "before": null,
          "after": false
        }
      ]
    },
    {
      "stable_id": "fifa-wc2026-match-027",
      "changes": [
        {
          "field": "is_brazil_match",
          "before": null,
          "after": false
        }
      ]
    },
    {
      "stable_id": "fifa-wc2026-match-028",
      "changes": [
        {
          "field": "is_brazil_match",
          "before": null,
          "after": false
        }
      ]
    },
    {
      "stable_id": "fifa-wc2026-match-029",
      "changes": [
        {
          "field": "is_brazil_match",
          "before": null,
          "after": true
        }
      ]
    },
    {
      "stable_id": "fifa-wc2026-match-030",
      "changes": [
        {
          "field": "is_brazil_match",
          "before": null,
          "after": false
        }
      ]
    },
    {
      "stable_id": "fifa-wc2026-match-031",
      "changes": [
        {
          "field": "is_brazil_match",
          "before": null,
          "after": false
        }
      ]
    },
    {
      "stable_id": "fifa-wc2026-match-032",
      "changes": [
        {
          "field": "is_brazil_match",
          "before": null,
          "after": false
        }
      ]
    },
    {
      "stable_id": "fifa-wc2026-match-033",
      "changes": [
        {
          "field": "is_brazil_match",
          "before": null,
          "after": false
        }
      ]
    },
    {
      "stable_id": "fifa-wc2026-match-034",
      "changes": [
        {
          "field": "is_brazil_match",
          "before": null,
          "after": false
        }
      ]
    },
    {
      "stable_id": "fifa-wc2026-match-035",
      "changes": [
        {
          "field": "is_brazil_match",
          "before": null,
          "after": false
        }
      ]
    },
    {
      "stable_id": "fifa-wc2026-match-036",
      "changes": [
        {
          "field": "is_brazil_match",
          "before": null,
          "after": false
        }
      ]
    },
    {
      "stable_id": "fifa-wc2026-match-037",
      "changes": [
        {
          "field": "is_brazil_match",
          "before": null,
          "after": false
        }
      ]
    },
    {
      "stable_id": "fifa-wc2026-match-038",
      "changes": [
        {
          "field": "is_brazil_match",
          "before": null,
          "after": false
        }
      ]
    },
    {
      "stable_id": "fifa-wc2026-match-039",
      "changes": [
        {
          "field": "is_brazil_match",
          "before": null,
          "after": false
        }
      ]
    },
    {
      "stable_id": "fifa-wc2026-match-040",
      "changes": [
        {
          "field": "is_brazil_match",
          "before": null,
          "after": false
        }
      ]
    },
    {
      "stable_id": "fifa-wc2026-match-041",
      "changes": [
        {
          "field": "is_brazil_match",
          "before": null,
          "after": false
        }
      ]
    },
    {
      "stable_id": "fifa-wc2026-match-042",
      "changes": [
        {
          "field": "is_brazil_match",
          "before": null,
          "after": false
        }
      ]
    },
    {
      "stable_id": "fifa-wc2026-match-043",
      "changes": [
        {
          "field": "is_brazil_match",
          "before": null,
          "after": false
        }
      ]
    },
    {
      "stable_id": "fifa-wc2026-match-044",
      "changes": [
        {
          "field": "is_brazil_match",
          "before": null,
          "after": false
        }
      ]
    },
    {
      "stable_id": "fifa-wc2026-match-045",
      "changes": [
        {
          "field": "is_brazil_match",
          "before": null,
          "after": false
        }
      ]
    },
    {
      "stable_id": "fifa-wc2026-match-046",
      "changes": [
        {
          "field": "is_brazil_match",
          "before": null,
          "after": false
        }
      ]
    },
    {
      "stable_id": "fifa-wc2026-match-047",
      "changes": [
        {
          "field": "is_brazil_match",
          "before": null,
          "after": false
        }
      ]
    },
    {
      "stable_id": "fifa-wc2026-match-048",
      "changes": [
        {
          "field": "is_brazil_match",
          "before": null,
          "after": false
        }
      ]
    },
    {
      "stable_id": "fifa-wc2026-match-049",
      "changes": [
        {
          "field": "is_brazil_match",
          "before": null,
          "after": true
        }
      ]
    },
    {
      "stable_id": "fifa-wc2026-match-050",
      "changes": [
        {
          "field": "is_brazil_match",
          "before": null,
          "after": false
        }
      ]
    },
    {
      "stable_id": "fifa-wc2026-match-051",
      "changes": [
        {
          "field": "is_brazil_match",
          "before": null,
          "after": false
        }
      ]
    },
    {
      "stable_id": "fifa-wc2026-match-052",
      "changes": [
        {
          "field": "is_brazil_match",
          "before": null,
          "after": false
        }
      ]
    },
    {
      "stable_id": "fifa-wc2026-match-053",
      "changes": [
        {
          "field": "is_brazil_match",
          "before": null,
          "after": false
        }
      ]
    },
    {
      "stable_id": "fifa-wc2026-match-054",
      "changes": [
        {
          "field": "is_brazil_match",
          "before": null,
          "after": false
        }
      ]
    },
    {
      "stable_id": "fifa-wc2026-match-055",
      "changes": [
        {
          "field": "is_brazil_match",
          "before": null,
          "after": false
        }
      ]
    },
    {
      "stable_id": "fifa-wc2026-match-056",
      "changes": [
        {
          "field": "is_brazil_match",
          "before": null,
          "after": false
        }
      ]
    },
    {
      "stable_id": "fifa-wc2026-match-057",
      "changes": [
        {
          "field": "is_brazil_match",
          "before": null,
          "after": false
        }
      ]
    },
    {
      "stable_id": "fifa-wc2026-match-058",
      "changes": [
        {
          "field": "is_brazil_match",
          "before": null,
          "after": false
        }
      ]
    },
    {
      "stable_id": "fifa-wc2026-match-059",
      "changes": [
        {
          "field": "is_brazil_match",
          "before": null,
          "after": false
        }
      ]
    },
    {
      "stable_id": "fifa-wc2026-match-060",
      "changes": [
        {
          "field": "is_brazil_match",
          "before": null,
          "after": false
        }
      ]
    },
    {
      "stable_id": "fifa-wc2026-match-061",
      "changes": [
        {
          "field": "is_brazil_match",
          "before": null,
          "after": false
        }
      ]
    },
    {
      "stable_id": "fifa-wc2026-match-062",
      "changes": [
        {
          "field": "is_brazil_match",
          "before": null,
          "after": false
        }
      ]
    },
    {
      "stable_id": "fifa-wc2026-match-063",
      "changes": [
        {
          "field": "is_brazil_match",
          "before": null,
          "after": false
        }
      ]
    },
    {
      "stable_id": "fifa-wc2026-match-064",
      "changes": [
        {
          "field": "is_brazil_match",
          "before": null,
          "after": false
        }
      ]
    },
    {
      "stable_id": "fifa-wc2026-match-065",
      "changes": [
        {
          "field": "is_brazil_match",
          "before": null,
          "after": false
        }
      ]
    },
    {
      "stable_id": "fifa-wc2026-match-066",
      "changes": [
        {
          "field": "is_brazil_match",
          "before": null,
          "after": false
        }
      ]
    },
    {
      "stable_id": "fifa-wc2026-match-067",
      "changes": [
        {
          "field": "is_brazil_match",
          "before": null,
          "after": false
        }
      ]
    },
    {
      "stable_id": "fifa-wc2026-match-068",
      "changes": [
        {
          "field": "is_brazil_match",
          "before": null,
          "after": false
        }
      ]
    },
    {
      "stable_id": "fifa-wc2026-match-069",
      "changes": [
        {
          "field": "is_brazil_match",
          "before": null,
          "after": false
        }
      ]
    },
    {
      "stable_id": "fifa-wc2026-match-070",
      "changes": [
        {
          "field": "is_brazil_match",
          "before": null,
          "after": false
        }
      ]
    },
    {
      "stable_id": "fifa-wc2026-match-071",
      "changes": [
        {
          "field": "is_brazil_match",
          "before": null,
          "after": false
        }
      ]
    },
    {
      "stable_id": "fifa-wc2026-match-072",
      "changes": [
        {
          "field": "is_brazil_match",
          "before": null,
          "after": false
        }
      ]
    },
    {
      "stable_id": "fifa-wc2026-match-073",
      "changes": [
        {
          "field": "is_brazil_match",
          "before": null,
          "after": false
        }
      ]
    },
    {
      "stable_id": "fifa-wc2026-match-074",
      "changes": [
        {
          "field": "is_brazil_match",
          "before": null,
          "after": false
        }
      ]
    },
    {
      "stable_id": "fifa-wc2026-match-075",
      "changes": [
        {
          "field": "is_brazil_match",
          "before": null,
          "after": false
        }
      ]
    },
    {
      "stable_id": "fifa-wc2026-match-076",
      "changes": [
        {
          "field": "is_brazil_match",
          "before": null,
          "after": false
        }
      ]
    },
    {
      "stable_id": "fifa-wc2026-match-077",
      "changes": [
        {
          "field": "is_brazil_match",
          "before": null,
          "after": false
        }
      ]
    },
    {
      "stable_id": "fifa-wc2026-match-078",
      "changes": [
        {
          "field": "is_brazil_match",
          "before": null,
          "after": false
        }
      ]
    },
    {
      "stable_id": "fifa-wc2026-match-079",
      "changes": [
        {
          "field": "is_brazil_match",
          "before": null,
          "after": false
        }
      ]
    },
    {
      "stable_id": "fifa-wc2026-match-080",
      "changes": [
        {
          "field": "is_brazil_match",
          "before": null,
          "after": false
        }
      ]
    },
    {
      "stable_id": "fifa-wc2026-match-081",
      "changes": [
        {
          "field": "is_brazil_match",
          "before": null,
          "after": false
        }
      ]
    },
    {
      "stable_id": "fifa-wc2026-match-082",
      "changes": [
        {
          "field": "is_brazil_match",
          "before": null,
          "after": false
        }
      ]
    },
    {
      "stable_id": "fifa-wc2026-match-083",
      "changes": [
        {
          "field": "is_brazil_match",
          "before": null,
          "after": false
        }
      ]
    },
    {
      "stable_id": "fifa-wc2026-match-084",
      "changes": [
        {
          "field": "is_brazil_match",
          "before": null,
          "after": false
        }
      ]
    },
    {
      "stable_id": "fifa-wc2026-match-085",
      "changes": [
        {
          "field": "is_brazil_match",
          "before": null,
          "after": false
        }
      ]
    },
    {
      "stable_id": "fifa-wc2026-match-086",
      "changes": [
        {
          "field": "is_brazil_match",
          "before": null,
          "after": false
        }
      ]
    },
    {
      "stable_id": "fifa-wc2026-match-087",
      "changes": [
        {
          "field": "is_brazil_match",
          "before": null,
          "after": false
        }
      ]
    },
    {
      "stable_id": "fifa-wc2026-match-088",
      "changes": [
        {
          "field": "is_brazil_match",
          "before": null,
          "after": false
        }
      ]
    },
    {
      "stable_id": "fifa-wc2026-match-089",
      "changes": [
        {
          "field": "is_brazil_match",
          "before": null,
          "after": false
        }
      ]
    },
    {
      "stable_id": "fifa-wc2026-match-090",
      "changes": [
        {
          "field": "is_brazil_match",
          "before": null,
          "after": false
        }
      ]
    },
    {
      "stable_id": "fifa-wc2026-match-091",
      "changes": [
        {
          "field": "is_brazil_match",
          "before": null,
          "after": false
        }
      ]
    },
    {
      "stable_id": "fifa-wc2026-match-092",
      "changes": [
        {
          "field": "is_brazil_match",
          "before": null,
          "after": false
        }
      ]
    },
    {
      "stable_id": "fifa-wc2026-match-093",
      "changes": [
        {
          "field": "is_brazil_match",
          "before": null,
          "after": false
        }
      ]
    },
    {
      "stable_id": "fifa-wc2026-match-094",
      "changes": [
        {
          "field": "is_brazil_match",
          "before": null,
          "after": false
        }
      ]
    },
    {
      "stable_id": "fifa-wc2026-match-095",
      "changes": [
        {
          "field": "is_brazil_match",
          "before": null,
          "after": false
        }
      ]
    },
    {
      "stable_id": "fifa-wc2026-match-096",
      "changes": [
        {
          "field": "is_brazil_match",
          "before": null,
          "after": false
        }
      ]
    },
    {
      "stable_id": "fifa-wc2026-match-097",
      "changes": [
        {
          "field": "is_brazil_match",
          "before": null,
          "after": false
        }
      ]
    },
    {
      "stable_id": "fifa-wc2026-match-098",
      "changes": [
        {
          "field": "is_brazil_match",
          "before": null,
          "after": false
        }
      ]
    },
    {
      "stable_id": "fifa-wc2026-match-099",
      "changes": [
        {
          "field": "is_brazil_match",
          "before": null,
          "after": false
        }
      ]
    },
    {
      "stable_id": "fifa-wc2026-match-100",
      "changes": [
        {
          "field": "is_brazil_match",
          "before": null,
          "after": false
        }
      ]
    },
    {
      "stable_id": "fifa-wc2026-match-101",
      "changes": [
        {
          "field": "is_brazil_match",
          "before": null,
          "after": false
        }
      ]
    },
    {
      "stable_id": "fifa-wc2026-match-102",
      "changes": [
        {
          "field": "is_brazil_match",
          "before": null,
          "after": false
        }
      ]
    },
    {
      "stable_id": "fifa-wc2026-match-103",
      "changes": [
        {
          "field": "is_brazil_match",
          "before": null,
          "after": false
        }
      ]
    },
    {
      "stable_id": "fifa-wc2026-match-104",
      "changes": [
        {
          "field": "is_brazil_match",
          "before": null,
          "after": false
        }
      ]
    }
  ]
}
